{
  "fio version" : "fio-3.8",
  "timestamp" : 1553074398,
  "timestamp_ms" : 1553074398573,
  "time" : "Wed Mar 20 02:33:18 2019",
  "jobs" : [
    {
      "jobname" : "wipc",
      "groupid" : 0,
      "error" : 0,
      "eta" : 0,
      "elapsed" : 1428,
      "job options" : {
        "ioengine" : "libaio",
        "group_reporting" : "1",
        "direct" : "1",
        "rw" : "write",
        "bssplit" : "128KB",
        "numjobs" : "2",
        "iodepth" : "16",
        "size" : "75%",
        "io_size" : "128035676160B",
        "filename" : "/dev/sdc"
      },
      "read" : {
        "io_bytes" : 0,
        "io_kbytes" : 0,
        "bw_bytes" : 0,
        "bw" : 0,
        "iops" : 0.000000,
        "runtime" : 0,
        "total_ios" : 0,
        "short_ios" : 0,
        "drop_ios" : 0,
        "slat_ns" : {
          "min" : 0,
          "max" : 0,
          "mean" : 0.000000,
          "stddev" : 0.000000
        },
        "clat_ns" : {
          "min" : 0,
          "max" : 0,
          "mean" : 0.000000,
          "stddev" : 0.000000,
          "percentile" : {
            "1.000000" : 0,
            "5.000000" : 0,
            "10.000000" : 0,
            "20.000000" : 0,
            "30.000000" : 0,
            "40.000000" : 0,
            "50.000000" : 0,
            "60.000000" : 0,
            "70.000000" : 0,
            "80.000000" : 0,
            "90.000000" : 0,
            "95.000000" : 0,
            "99.000000" : 0,
            "99.500000" : 0,
            "99.900000" : 0,
            "99.950000" : 0,
            "99.990000" : 0
          },
          "bins" : {

          }
        },
        "lat_ns" : {
          "min" : 0,
          "max" : 0,
          "mean" : 0.000000,
          "stddev" : 0.000000
        },
        "bw_min" : 0,
        "bw_max" : 0,
        "bw_agg" : 0.000000,
        "bw_mean" : 0.000000,
        "bw_dev" : 0.000000,
        "bw_samples" : 0,
        "iops_min" : 0,
        "iops_max" : 0,
        "iops_mean" : 0.000000,
        "iops_stddev" : 0.000000,
        "iops_samples" : 0
      },
      "write" : {
        "io_bytes" : 256071434240,
        "io_kbytes" : 250069760,
        "bw_bytes" : 179351498,
        "bw" : 175147,
        "iops" : 1368.343345,
        "runtime" : 1427763,
        "total_ios" : 1953670,
        "short_ios" : 0,
        "drop_ios" : 0,
        "slat_ns" : {
          "min" : 6750,
          "max" : 315857,
          "mean" : 16487.513290,
          "stddev" : 4675.760490
        },
        "clat_ns" : {
          "min" : 834544,
          "max" : 122358893,
          "mean" : 23364114.938272,
          "stddev" : 15473376.569326,
          "percentile" : {
            "1.000000" : 12910592,
            "5.000000" : 13172736,
            "10.000000" : 13303808,
            "20.000000" : 13565952,
            "30.000000" : 13828096,
            "40.000000" : 14090240,
            "50.000000" : 14483456,
            "60.000000" : 15007744,
            "70.000000" : 16711680,
            "80.000000" : 36962304,
            "90.000000" : 54788096,
            "95.000000" : 57933824,
            "99.000000" : 63700992,
            "99.500000" : 65798144,
            "99.900000" : 76021760,
            "99.950000" : 81264640,
            "99.990000" : 98041856
          },
          "bins" : {
            "831488" : 1,
            "1318912" : 1,
            "1433600" : 1,
            "2072576" : 1,
            "2506752" : 1,
            "2801664" : 1,
            "3293184" : 1,
            "3686400" : 1,
            "4112384" : 1,
            "4489216" : 1,
            "4882432" : 1,
            "5406720" : 1,
            "5734400" : 1,
            "6127616" : 1,
            "6520832" : 1,
            "6914048" : 1,
            "7241728" : 1,
            "7634944" : 1,
            "8028160" : 1,
            "8355840" : 1,
            "8716288" : 1,
            "9109504" : 1,
            "9895936" : 1,
            "10158080" : 1,
            "10551296" : 1,
            "10944512" : 1,
            "11206656" : 5,
            "11337728" : 13,
            "11468800" : 43,
            "11599872" : 72,
            "11730944" : 113,
            "11862016" : 149,
            "11993088" : 191,
            "12124160" : 224,
            "12255232" : 324,
            "12386304" : 449,
            "12517376" : 971,
            "12648448" : 2300,
            "12779520" : 5553,
            "12910592" : 14334,
            "13041664" : 32395,
            "13172736" : 59419,
            "13303808" : 84622,
            "13434880" : 101923,
            "13565952" : 109891,
            "13697024" : 107743,
            "13828096" : 101892,
            "13959168" : 94377,
            "14090240" : 86536,
            "14221312" : 78443,
            "14352384" : 67556,
            "14483456" : 60066,
            "14614528" : 54353,
            "14745600" : 47743,
            "14876672" : 42836,
            "15007744" : 38479,
            "15138816" : 35558,
            "15269888" : 32004,
            "15400960" : 26891,
            "15532032" : 21790,
            "15663104" : 16933,
            "15794176" : 13241,
            "15925248" : 8979,
            "16056320" : 6450,
            "16187392" : 4257,
            "16318464" : 3211,
            "16449536" : 2597,
            "16580608" : 1800,
            "16711680" : 1434,
            "16908288" : 2371,
            "17170432" : 1682,
            "17432576" : 857,
            "17694720" : 467,
            "17956864" : 284,
            "18219008" : 147,
            "18481152" : 67,
            "18743296" : 40,
            "19005440" : 31,
            "19267584" : 54,
            "19529728" : 65,
            "19791872" : 59,
            "20054016" : 60,
            "20316160" : 44,
            "20578304" : 31,
            "20840448" : 87,
            "21102592" : 81,
            "21364736" : 70,
            "21626880" : 48,
            "21889024" : 36,
            "22151168" : 24,
            "22413312" : 23,
            "22675456" : 15,
            "22937600" : 27,
            "23199744" : 6,
            "23461888" : 12,
            "23724032" : 5,
            "23986176" : 4,
            "24248320" : 15,
            "24510464" : 15,
            "24772608" : 7,
            "25034752" : 15,
            "25296896" : 25,
            "25559040" : 38,
            "25821184" : 109,
            "26083328" : 184,
            "26345472" : 442,
            "26607616" : 1673,
            "26869760" : 4056,
            "27131904" : 3941,
            "27394048" : 2813,
            "27656192" : 1790,
            "27918336" : 1399,
            "28180480" : 980,
            "28442624" : 747,
            "28704768" : 629,
            "28966912" : 404,
            "29229056" : 265,
            "29491200" : 207,
            "29753344" : 199,
            "30015488" : 176,
            "30277632" : 217,
            "30539776" : 328,
            "30801920" : 325,
            "31064064" : 411,
            "31326208" : 439,
            "31588352" : 524,
            "31850496" : 627,
            "32112640" : 785,
            "32374784" : 1112,
            "32636928" : 1451,
            "32899072" : 1755,
            "33161216" : 2363,
            "33423360" : 3161,
            "33816576" : 8937,
            "34340864" : 13506,
            "34865152" : 18625,
            "35389440" : 23236,
            "35913728" : 29259,
            "36438016" : 33905,
            "36962304" : 32545,
            "37486592" : 28589,
            "38010880" : 27532,
            "38535168" : 23788,
            "39059456" : 15580,
            "39583744" : 10605,
            "40108032" : 8293,
            "40632320" : 7034,
            "41156608" : 6061,
            "41680896" : 5635,
            "42205184" : 5331,
            "42729472" : 4656,
            "43253760" : 3692,
            "43778048" : 2680,
            "44302336" : 1720,
            "44826624" : 1099,
            "45350912" : 609,
            "45875200" : 382,
            "46399488" : 282,
            "46923776" : 339,
            "47448064" : 393,
            "47972352" : 559,
            "48496640" : 417,
            "49020928" : 334,
            "49545216" : 457,
            "50069504" : 457,
            "50593792" : 523,
            "51118080" : 795,
            "51642368" : 1299,
            "52166656" : 2175,
            "52690944" : 3449,
            "53215232" : 4886,
            "53739520" : 6322,
            "54263808" : 9039,
            "54788096" : 13806,
            "55312384" : 18071,
            "55836672" : 18975,
            "56360960" : 16696,
            "56885248" : 14985,
            "57409536" : 16952,
            "57933824" : 16249,
            "58458112" : 11484,
            "58982400" : 7620,
            "59506688" : 6709,
            "60030976" : 6213,
            "60555264" : 5816,
            "61079552" : 5580,
            "61603840" : 5427,
            "62128128" : 5276,
            "62652416" : 5081,
            "63176704" : 4369,
            "63700992" : 3449,
            "64225280" : 2902,
            "64749568" : 2422,
            "65273856" : 2060,
            "65798144" : 1626,
            "66322432" : 1154,
            "66846720" : 838,
            "67633152" : 1193,
            "68681728" : 741,
            "69730304" : 488,
            "70778880" : 501,
            "71827456" : 386,
            "72876032" : 383,
            "73924608" : 406,
            "74973184" : 239,
            "76021760" : 188,
            "77070336" : 287,
            "78118912" : 227,
            "79167488" : 146,
            "80216064" : 116,
            "81264640" : 117,
            "82313216" : 96,
            "83361792" : 48,
            "84410368" : 56,
            "85458944" : 66,
            "86507520" : 74,
            "87556096" : 60,
            "88604672" : 54,
            "89653248" : 46,
            "90701824" : 54,
            "91750400" : 48,
            "92798976" : 38,
            "93847552" : 33,
            "94896128" : 38,
            "95944704" : 26,
            "96993280" : 24,
            "98041856" : 14,
            "99090432" : 17,
            "100139008" : 18,
            "101187584" : 13,
            "102236160" : 22,
            "103284736" : 15,
            "104333312" : 9,
            "105381888" : 25,
            "106430464" : 25,
            "107479040" : 6,
            "108527616" : 6,
            "109576192" : 7,
            "110624768" : 2,
            "111673344" : 3,
            "112721920" : 2,
            "113770496" : 3,
            "114819072" : 2,
            "115867648" : 1,
            "116916224" : 2,
            "119013376" : 2,
            "122159104" : 2
          }
        },
        "lat_ns" : {
          "min" : 878115,
          "max" : 122375839,
          "mean" : 23380917.501072,
          "stddev" : 15474947.932800
        },
        "bw_min" : 30464,
        "bw_max" : 151296,
        "bw_agg" : 49.999582,
        "bw_mean" : 87572.767951,
        "bw_dev" : 47176.781986,
        "bw_samples" : 5710,
        "iops_min" : 238,
        "iops_max" : 1182,
        "iops_mean" : 684.145709,
        "iops_stddev" : 368.559587,
        "iops_samples" : 5710
      },
      "trim" : {
        "io_bytes" : 0,
        "io_kbytes" : 0,
        "bw_bytes" : 0,
        "bw" : 0,
        "iops" : 0.000000,
        "runtime" : 0,
        "total_ios" : 0,
        "short_ios" : 0,
        "drop_ios" : 0,
        "slat_ns" : {
          "min" : 0,
          "max" : 0,
          "mean" : 0.000000,
          "stddev" : 0.000000
        },
        "clat_ns" : {
          "min" : 0,
          "max" : 0,
          "mean" : 0.000000,
          "stddev" : 0.000000,
          "percentile" : {
            "1.000000" : 0,
            "5.000000" : 0,
            "10.000000" : 0,
            "20.000000" : 0,
            "30.000000" : 0,
            "40.000000" : 0,
            "50.000000" : 0,
            "60.000000" : 0,
            "70.000000" : 0,
            "80.000000" : 0,
            "90.000000" : 0,
            "95.000000" : 0,
            "99.000000" : 0,
            "99.500000" : 0,
            "99.900000" : 0,
            "99.950000" : 0,
            "99.990000" : 0
          },
          "bins" : {

          }
        },
        "lat_ns" : {
          "min" : 0,
          "max" : 0,
          "mean" : 0.000000,
          "stddev" : 0.000000
        },
        "bw_min" : 0,
        "bw_max" : 0,
        "bw_agg" : 0.000000,
        "bw_mean" : 0.000000,
        "bw_dev" : 0.000000,
        "bw_samples" : 0,
        "iops_min" : 0,
        "iops_max" : 0,
        "iops_mean" : 0.000000,
        "iops_stddev" : 0.000000,
        "iops_samples" : 0
      },
      "sync" : {
        "lat_ns" : {
          "min" : 0,
          "max" : 0,
          "mean" : 0.000000,
          "stddev" : 0.000000,
          "percentile" : {
            "1.000000" : 0,
            "5.000000" : 0,
            "10.000000" : 0,
            "20.000000" : 0,
            "30.000000" : 0,
            "40.000000" : 0,
            "50.000000" : 0,
            "60.000000" : 0,
            "70.000000" : 0,
            "80.000000" : 0,
            "90.000000" : 0,
            "95.000000" : 0,
            "99.000000" : 0,
            "99.500000" : 0,
            "99.900000" : 0,
            "99.950000" : 0,
            "99.990000" : 0
          },
          "bins" : {

          }
        },
        "total_ios" : 0
      },
      "job_runtime" : 2855357,
      "usr_cpu" : 1.050377,
      "sys_cpu" : 1.404658,
      "ctx" : 1893238,
      "majf" : 0,
      "minf" : 8015,
      "iodepth_level" : {
        "1" : 0.100000,
        "2" : 0.100000,
        "4" : 0.100000,
        "8" : 0.100000,
        "16" : 99.996929,
        "32" : 0.000000,
        ">=64" : 0.000000
      },
      "latency_ns" : {
        "2" : 0.000000,
        "4" : 0.000000,
        "10" : 0.000000,
        "20" : 0.000000,
        "50" : 0.000000,
        "100" : 0.000000,
        "250" : 0.000000,
        "500" : 0.000000,
        "750" : 0.000000,
        "1000" : 0.000000
      },
      "latency_us" : {
        "2" : 0.000000,
        "4" : 0.000000,
        "10" : 0.000000,
        "20" : 0.000000,
        "50" : 0.000000,
        "100" : 0.000000,
        "250" : 0.000000,
        "500" : 0.000000,
        "750" : 0.000000,
        "1000" : 0.010000
      },
      "latency_ms" : {
        "2" : 0.010000,
        "4" : 0.010000,
        "10" : 0.010000,
        "20" : 70.344941,
        "50" : 17.937062,
        "100" : 11.708784,
        "250" : 0.010000,
        "500" : 0.000000,
        "750" : 0.000000,
        "1000" : 0.000000,
        "2000" : 0.000000,
        ">=2000" : 0.000000
      },
      "latency_depth" : 16,
      "latency_target" : 0,
      "latency_percentile" : 100.000000,
      "latency_window" : 0
    }
  ],
  "disk_util" : [
    {
      "name" : "sdc",
      "read_ios" : 128,
      "write_ios" : 1953528,
      "read_merges" : 0,
      "write_merges" : 43,
      "read_ticks" : 456,
      "write_ticks" : 45611328,
      "in_queue" : 45611544,
      "util" : 100.000000
    }
  ]
}
