{
  "fio version" : "fio-3.8",
  "timestamp" : 1546129027,
  "timestamp_ms" : 1546129027003,
  "time" : "Sat Dec 29 16:17:07 2018",
  "jobs" : [
    {
      "jobname" : "wipc",
      "groupid" : 0,
      "error" : 0,
      "eta" : 0,
      "elapsed" : 1518,
      "job options" : {
        "ioengine" : "libaio",
        "group_reporting" : "1",
        "direct" : "1",
        "rw" : "write",
        "bssplit" : "128KB",
        "numjobs" : "2",
        "iodepth" : "16",
        "size" : "100%",
        "io_size" : "128035676160B",
        "filename" : "/dev/sdf"
      },
      "read" : {
        "io_bytes" : 0,
        "io_kbytes" : 0,
        "bw_bytes" : 0,
        "bw" : 0,
        "iops" : 0.000000,
        "runtime" : 0,
        "total_ios" : 0,
        "short_ios" : 0,
        "drop_ios" : 0,
        "slat_ns" : {
          "min" : 0,
          "max" : 0,
          "mean" : 0.000000,
          "stddev" : 0.000000
        },
        "clat_ns" : {
          "min" : 0,
          "max" : 0,
          "mean" : 0.000000,
          "stddev" : 0.000000,
          "percentile" : {
            "1.000000" : 0,
            "5.000000" : 0,
            "10.000000" : 0,
            "20.000000" : 0,
            "30.000000" : 0,
            "40.000000" : 0,
            "50.000000" : 0,
            "60.000000" : 0,
            "70.000000" : 0,
            "80.000000" : 0,
            "90.000000" : 0,
            "95.000000" : 0,
            "99.000000" : 0,
            "99.500000" : 0,
            "99.900000" : 0,
            "99.950000" : 0,
            "99.990000" : 0
          },
          "bins" : {

          }
        },
        "lat_ns" : {
          "min" : 0,
          "max" : 0,
          "mean" : 0.000000,
          "stddev" : 0.000000
        },
        "bw_min" : 0,
        "bw_max" : 0,
        "bw_agg" : 0.000000,
        "bw_mean" : 0.000000,
        "bw_dev" : 0.000000,
        "bw_samples" : 0,
        "iops_min" : 0,
        "iops_max" : 0,
        "iops_mean" : 0.000000,
        "iops_stddev" : 0.000000,
        "iops_samples" : 0
      },
      "write" : {
        "io_bytes" : 256071172096,
        "io_kbytes" : 250069504,
        "bw_bytes" : 168737078,
        "bw" : 164782,
        "iops" : 1287.361745,
        "runtime" : 1517575,
        "total_ios" : 1953668,
        "short_ios" : 0,
        "drop_ios" : 0,
        "slat_ns" : {
          "min" : 6207,
          "max" : 249875,
          "mean" : 17184.406064,
          "stddev" : 5657.589704
        },
        "clat_ns" : {
          "min" : 807248,
          "max" : 92211102,
          "mean" : 24824953.334681,
          "stddev" : 16432876.508657,
          "percentile" : {
            "1.000000" : 12910592,
            "5.000000" : 13041664,
            "10.000000" : 13303808,
            "20.000000" : 13565952,
            "30.000000" : 13828096,
            "40.000000" : 14090240,
            "50.000000" : 14614528,
            "60.000000" : 15269888,
            "70.000000" : 34340864,
            "80.000000" : 38010880,
            "90.000000" : 55312384,
            "95.000000" : 57933824,
            "99.000000" : 63176704,
            "99.500000" : 64749568,
            "99.900000" : 72876032,
            "99.950000" : 77070336,
            "99.990000" : 82313216
          },
          "bins" : {
            "806912" : 1,
            "1286144" : 1,
            "1384448" : 1,
            "2056192" : 1,
            "2408448" : 1,
            "2768896" : 1,
            "3227648" : 1,
            "3588096" : 1,
            "3948544" : 1,
            "4358144" : 1,
            "4685824" : 1,
            "5079040" : 1,
            "5537792" : 1,
            "5865472" : 1,
            "6258688" : 1,
            "6586368" : 1,
            "6914048" : 1,
            "7307264" : 1,
            "7634944" : 1,
            "8028160" : 1,
            "8454144" : 1,
            "8716288" : 1,
            "9764864" : 1,
            "10027008" : 1,
            "10420224" : 1,
            "10813440" : 1,
            "11599872" : 4,
            "11730944" : 14,
            "11862016" : 36,
            "11993088" : 92,
            "12124160" : 139,
            "12255232" : 243,
            "12386304" : 465,
            "12517376" : 1255,
            "12648448" : 4202,
            "12779520" : 12438,
            "12910592" : 32606,
            "13041664" : 61073,
            "13172736" : 81893,
            "13303808" : 92660,
            "13434880" : 95201,
            "13565952" : 96144,
            "13697024" : 93605,
            "13828096" : 84881,
            "13959168" : 72066,
            "14090240" : 59968,
            "14221312" : 53461,
            "14352384" : 54377,
            "14483456" : 56441,
            "14614528" : 53435,
            "14745600" : 46891,
            "14876672" : 40735,
            "15007744" : 35305,
            "15138816" : 32180,
            "15269888" : 26895,
            "15400960" : 22493,
            "15532032" : 17817,
            "15663104" : 14335,
            "15794176" : 11226,
            "15925248" : 8525,
            "16056320" : 6140,
            "16187392" : 5263,
            "16318464" : 4086,
            "16449536" : 3056,
            "16580608" : 2924,
            "16711680" : 2361,
            "16908288" : 3478,
            "17170432" : 2123,
            "17432576" : 1076,
            "17694720" : 492,
            "17956864" : 263,
            "18219008" : 177,
            "18481152" : 152,
            "18743296" : 94,
            "19005440" : 111,
            "19267584" : 87,
            "19529728" : 99,
            "19791872" : 108,
            "20054016" : 121,
            "20316160" : 92,
            "20578304" : 116,
            "20840448" : 84,
            "21102592" : 89,
            "21364736" : 63,
            "21626880" : 48,
            "21889024" : 66,
            "22151168" : 54,
            "22413312" : 44,
            "22675456" : 23,
            "22937600" : 16,
            "23199744" : 15,
            "23461888" : 20,
            "23724032" : 11,
            "23986176" : 12,
            "24248320" : 1,
            "24510464" : 4,
            "24772608" : 2,
            "25034752" : 5,
            "25296896" : 14,
            "25559040" : 40,
            "25821184" : 95,
            "26083328" : 202,
            "26345472" : 473,
            "26607616" : 1843,
            "26869760" : 4689,
            "27131904" : 4381,
            "27394048" : 2117,
            "27656192" : 1370,
            "27918336" : 847,
            "28180480" : 586,
            "28442624" : 515,
            "28704768" : 417,
            "28966912" : 247,
            "29229056" : 228,
            "29491200" : 200,
            "29753344" : 195,
            "30015488" : 220,
            "30277632" : 283,
            "30539776" : 355,
            "30801920" : 425,
            "31064064" : 555,
            "31326208" : 636,
            "31588352" : 812,
            "31850496" : 1119,
            "32112640" : 1383,
            "32374784" : 1810,
            "32636928" : 2479,
            "32899072" : 3178,
            "33161216" : 4473,
            "33423360" : 5514,
            "33816576" : 15247,
            "34340864" : 20356,
            "34865152" : 26577,
            "35389440" : 33722,
            "35913728" : 36272,
            "36438016" : 33021,
            "36962304" : 30287,
            "37486592" : 27313,
            "38010880" : 19903,
            "38535168" : 13179,
            "39059456" : 9520,
            "39583744" : 7757,
            "40108032" : 6815,
            "40632320" : 6166,
            "41156608" : 5724,
            "41680896" : 4847,
            "42205184" : 3823,
            "42729472" : 2806,
            "43253760" : 1939,
            "43778048" : 1384,
            "44302336" : 854,
            "44826624" : 488,
            "45350912" : 326,
            "45875200" : 222,
            "46399488" : 165,
            "46923776" : 166,
            "47448064" : 229,
            "47972352" : 343,
            "48496640" : 401,
            "49020928" : 537,
            "49545216" : 624,
            "50069504" : 545,
            "50593792" : 797,
            "51118080" : 1255,
            "51642368" : 2240,
            "52166656" : 4356,
            "52690944" : 6652,
            "53215232" : 9017,
            "53739520" : 14429,
            "54263808" : 22358,
            "54788096" : 26667,
            "55312384" : 24266,
            "55836672" : 22796,
            "56360960" : 24045,
            "56885248" : 21619,
            "57409536" : 16248,
            "57933824" : 11558,
            "58458112" : 9800,
            "58982400" : 9296,
            "59506688" : 8737,
            "60030976" : 8469,
            "60555264" : 8421,
            "61079552" : 8537,
            "61603840" : 7714,
            "62128128" : 6518,
            "62652416" : 5492,
            "63176704" : 4661,
            "63700992" : 3862,
            "64225280" : 2802,
            "64749568" : 2111,
            "65273856" : 1672,
            "65798144" : 1300,
            "66322432" : 939,
            "66846720" : 596,
            "67633152" : 726,
            "68681728" : 704,
            "69730304" : 633,
            "70778880" : 527,
            "71827456" : 361,
            "72876032" : 442,
            "73924608" : 271,
            "74973184" : 127,
            "76021760" : 150,
            "77070336" : 215,
            "78118912" : 296,
            "79167488" : 242,
            "80216064" : 96,
            "81264640" : 65,
            "82313216" : 55,
            "83361792" : 60,
            "84410368" : 25,
            "85458944" : 22,
            "86507520" : 18,
            "87556096" : 17,
            "88604672" : 13,
            "89653248" : 8,
            "90701824" : 1,
            "91750400" : 2
          }
        },
        "lat_ns" : {
          "min" : 843850,
          "max" : 92230123,
          "mean" : 24842472.332092,
          "stddev" : 16433778.709364
        },
        "bw_min" : 32256,
        "bw_max" : 151552,
        "bw_agg" : 50.022749,
        "bw_mean" : 82428.486896,
        "bw_dev" : 46684.366530,
        "bw_samples" : 6067,
        "iops_min" : 252,
        "iops_max" : 1184,
        "iops_mean" : 643.965222,
        "iops_stddev" : 364.716954,
        "iops_samples" : 6067
      },
      "trim" : {
        "io_bytes" : 0,
        "io_kbytes" : 0,
        "bw_bytes" : 0,
        "bw" : 0,
        "iops" : 0.000000,
        "runtime" : 0,
        "total_ios" : 0,
        "short_ios" : 0,
        "drop_ios" : 0,
        "slat_ns" : {
          "min" : 0,
          "max" : 0,
          "mean" : 0.000000,
          "stddev" : 0.000000
        },
        "clat_ns" : {
          "min" : 0,
          "max" : 0,
          "mean" : 0.000000,
          "stddev" : 0.000000,
          "percentile" : {
            "1.000000" : 0,
            "5.000000" : 0,
            "10.000000" : 0,
            "20.000000" : 0,
            "30.000000" : 0,
            "40.000000" : 0,
            "50.000000" : 0,
            "60.000000" : 0,
            "70.000000" : 0,
            "80.000000" : 0,
            "90.000000" : 0,
            "95.000000" : 0,
            "99.000000" : 0,
            "99.500000" : 0,
            "99.900000" : 0,
            "99.950000" : 0,
            "99.990000" : 0
          },
          "bins" : {

          }
        },
        "lat_ns" : {
          "min" : 0,
          "max" : 0,
          "mean" : 0.000000,
          "stddev" : 0.000000
        },
        "bw_min" : 0,
        "bw_max" : 0,
        "bw_agg" : 0.000000,
        "bw_mean" : 0.000000,
        "bw_dev" : 0.000000,
        "bw_samples" : 0,
        "iops_min" : 0,
        "iops_max" : 0,
        "iops_mean" : 0.000000,
        "iops_stddev" : 0.000000,
        "iops_samples" : 0
      },
      "sync" : {
        "lat_ns" : {
          "min" : 0,
          "max" : 0,
          "mean" : 0.000000,
          "stddev" : 0.000000,
          "percentile" : {
            "1.000000" : 0,
            "5.000000" : 0,
            "10.000000" : 0,
            "20.000000" : 0,
            "30.000000" : 0,
            "40.000000" : 0,
            "50.000000" : 0,
            "60.000000" : 0,
            "70.000000" : 0,
            "80.000000" : 0,
            "90.000000" : 0,
            "95.000000" : 0,
            "99.000000" : 0,
            "99.500000" : 0,
            "99.900000" : 0,
            "99.950000" : 0,
            "99.990000" : 0
          },
          "bins" : {

          }
        },
        "total_ios" : 0
      },
      "job_runtime" : 3033678,
      "usr_cpu" : 1.054957,
      "sys_cpu" : 1.471745,
      "ctx" : 1883773,
      "majf" : 0,
      "minf" : 14717,
      "iodepth_level" : {
        "1" : 0.100000,
        "2" : 0.100000,
        "4" : 0.100000,
        "8" : 0.100000,
        "16" : 99.998464,
        "32" : 0.000000,
        ">=64" : 0.000000
      },
      "latency_ns" : {
        "2" : 0.000000,
        "4" : 0.000000,
        "10" : 0.000000,
        "20" : 0.000000,
        "50" : 0.000000,
        "100" : 0.000000,
        "250" : 0.000000,
        "500" : 0.000000,
        "750" : 0.000000,
        "1000" : 0.000000
      },
      "latency_us" : {
        "2" : 0.000000,
        "4" : 0.000000,
        "10" : 0.000000,
        "20" : 0.000000,
        "50" : 0.000000,
        "100" : 0.000000,
        "250" : 0.000000,
        "500" : 0.000000,
        "750" : 0.000000,
        "1000" : 0.010000
      },
      "latency_ms" : {
        "2" : 0.010000,
        "4" : 0.010000,
        "10" : 0.010000,
        "20" : 66.297498,
        "50" : 18.106710,
        "100" : 15.594615,
        "250" : 0.000000,
        "500" : 0.000000,
        "750" : 0.000000,
        "1000" : 0.000000,
        "2000" : 0.000000,
        ">=2000" : 0.000000
      },
      "latency_depth" : 16,
      "latency_target" : 0,
      "latency_percentile" : 100.000000,
      "latency_window" : 0
    }
  ],
  "disk_util" : [
    {
      "name" : "sdf",
      "read_ios" : 123,
      "write_ios" : 1953130,
      "read_merges" : 0,
      "write_merges" : 425,
      "read_ticks" : 244,
      "write_ticks" : 48458356,
      "in_queue" : 48458460,
      "util" : 100.000000
    }
  ]
}
